pyguards/__init__.py
pyguards/errors.py
pyguards/checkers/__init__.py
pyguards/checkers/bounds.py
pyguards/checkers/defined.py
pyguards/checkers/dict.py
pyguards/checkers/list.py
pyguards/checkers/rgb.py
pyguards/checkers/type.py
pyguards-0.0.3.dist-info/LICENSE
pyguards-0.0.3.dist-info/METADATA
pyguards-0.0.3.dist-info/WHEEL
pyguards-0.0.3.dist-info/top_level.txt
pyguards-0.0.3.dist-info/RECORD
